{
    "method": "efsmt",
    "lang": "chc",
    "template": "bv_zone",
    "smt_solver": "mathsat",
    "strengthen": true,
    "file": "s_split_28.smt2unsafe_64bits_signed.smt2",
    "overflow": false,
    "underflow": false,
    "unknown": true,
    "time": 3.8871121406555176,
    "message": [
        "Finish parsing CHC file",
        " prevent over/under flow?  False False",
        " Start solving: ",
        " Used template: TemplateType.BV_ZONE",
        " Used logic: BV",
        " EFSMT starting!!!",
        " EFSMT solver: mathsat",
        " unknown",
        ""
    ]
}