{
    "method": "efsmt",
    "lang": "chc",
    "template": "bv_interval",
    "smt_solver": "cegis",
    "cegis_solver": "btor",
    "file": "dec.sl_32bits_signed.smt2",
    "overflow": false,
    "underflow": false,
    "safe": true,
    "time": 19.846142292022705,
    "message": [
        "Finish parsing CHC file",
        " prevent over/under flow?  False False",
        " Start solving: ",
        " Used template: TemplateType.BV_INTERVAL",
        " Used logic: BV",
        " EFSMT starting!!!",
        " EFSMT solver: cegis",
        " solving via cegis_solver",
        " Simple, sequential, CEGIS-style EFSMT!",
        " safe",
        ""
    ]
}