{
    "method": "cvc5sys",
    "lang": "sygus",
    "file": "ex11-new.sl_64bits_unsigned.smt2_64bits_unsigned.sl",
    "unknown": true,
    "time": 2.6218137741088867,
    "message": [
        "(error \"Parse Error: /efmc/Benchmark/sygus/2016.SyGuS-Comp/64bits_unsigned/ex11-new.sl_64bits_unsigned.smt2_64bits_unsigned.sl:10.52: Sequence terminated early by token: '('.",
        " ",
        "   ...( let ( ( a!1 ( not ( and ( = ( ( _ extract (_ bv63 64) (_ bv6 64) ) c...",
        "                                                   ^",
        " \")",
        ""
    ]
}