{
    "method": "efsmt",
    "lang": "chc",
    "template": "bv_poly",
    "smt_solver": "mathsat",
    "file": "hhk2008_true-unreach-call_true-termination",
    "overflow": false,
    "underflow": false,
    "unknown": true,
    "time": 6.72856879234314,
    "message": [
        "Finish parsing CHC file",
        " prevent over/under flow?  False False",
        " Start solving: ",
        " Used template: TemplateType.BV_POLYHEDRON",
        " Used logic: BV",
        " EFSMT starting!!!",
        " EFSMT solver: mathsat",
        " unknown",
        ""
    ]
}