{
    "method": "efsmt",
    "lang": "chc",
    "template": "bv_poly",
    "smt_solver": "btor",
    "file": "array",
    "overflow": false,
    "underflow": false,
    "unknown": true,
    "time": 34.86359977722168,
    "message": [
        "Finish parsing CHC file",
        " prevent over/under flow?  False False",
        " Start solving: ",
        " Used template: TemplateType.BV_POLYHEDRON",
        " Used logic: BV",
        " EFSMT starting!!!",
        " EFSMT solver: btor",
        " Can not find corresponding solver",
        " unknown",
        ""
    ]
}