{
    "method": "cvc5sys",
    "lang": "sygus",
    "file": "non-lin-ineq-4.desugared.sl_64bits_unsigned.smt2_64bits_unsigned.sl",
    "unexpected_error": true,
    "time": 6.958615303039551,
    "message": [
        "(",
        " (define-fun inv_fun ((k (_ BitVec 64)) (j (_ BitVec 64)) (i (_ BitVec 64))) Bool (or (bvult i #b0000000000000000000000000000000000000000000000000000001111101000) (not (bvult k (bvmul j #b0000000000000000000000000000000000000000000000000000001111101000)))))",
        " )",
        ""
    ]
}