{
    "method": "efsmt",
    "lang": "chc",
    "template": "bv_interval",
    "smt_solver": "cegis",
    "cegis_solver": "cvc4",
    "file": "sum03_true-unreach-call_false-termination",
    "overflow": false,
    "underflow": false,
    "unknown": true,
    "time": 26.187072277069092,
    "message": [
        "Finish parsing CHC file",
        " prevent over/under flow?  False False",
        " Start solving: ",
        " Used template: TemplateType.BV_INTERVAL",
        " Used logic: BV",
        " EFSMT starting!!!",
        " EFSMT solver: cegis",
        " solving via cegis_solver",
        " Simple, sequential, CEGIS-style EFSMT!",
        " unknown",
        ""
    ]
}